LICENSE
MANIFEST.in
README.md
pyproject.toml
setup.py
anaio/__init__.py
anaio/anaio.py
anaio.egg-info/PKG-INFO
anaio.egg-info/SOURCES.txt
anaio.egg-info/dependency_links.txt
anaio.egg-info/requires.txt
anaio.egg-info/top_level.txt
anaio/__pycache__/__init__.cpython-38.pyc
anaio/__pycache__/__init__.cpython-39.pyc
anaio/__pycache__/anaio.cpython-38.pyc
anaio/__pycache__/anaio.cpython-39.pyc
src/_anaio.c
src/anacompress.c
src/anacompress.h
src/anadecompress.c
src/anadecompress.h
src/anarw.c
src/anarw.h
src/testrw.c
src/types.h