Metadata-Version: 2.4
Name: anaio
Version: 2.0.0
Summary: Python library for ANA f0 file I/O
Home-page: https://gitlab.gwdg.de/hoelken/anaio
Author: Johannes Hoelken
Author-email: hoelken@mps.mpg.de
License: MIT
Classifier: Programming Language :: Python :: 3
Classifier: License :: OSI Approved :: MIT License
Classifier: Operating System :: OS Independent
License-File: LICENSE
Requires-Dist: numpy>=2.0
Dynamic: author
Dynamic: author-email
Dynamic: classifier
Dynamic: description
Dynamic: description-content-type
Dynamic: home-page
Dynamic: license
Dynamic: license-file
Dynamic: requires-dist
Dynamic: summary
